{
  "id": "bishop-s-sutton-so24",
  "name": "Bishop's Sutton",
  "village": "Bishop's Sutton",
  "town": "Winchester",
  "county": "Hampshire",
  "postcode": "SO24",
  "hubCity": "Southampton",
  "regionDir": "North",
  "settlementType": "Non-City",
  "subRegion": "Winchester",
  "coords": {
    "lat": 51.10936,
    "lng": -1.17008
  },
  "coordsSource": "postcode-outward-approx",
  "houseTypeIds": [],
  "status": "directory",
  "overview": "",
  "character": "",
  "amenities": [],
  "schools": [],
  "transport": {
    "commutes": []
  },
  "prices": {},
  "thingsToDo": [],
  "placesToEat": [],
  "pros": [],
  "cons": [],
  "whoItSuits": [],
  "images": [],
  "sources": []
}
